word_to_pdf_converter/__init__.py
word_to_pdf_converter/convert.py
word_to_pdf_converter-0.1.1.dist-info/METADATA
word_to_pdf_converter-0.1.1.dist-info/WHEEL
word_to_pdf_converter-0.1.1.dist-info/RECORD
