Metadata-Version: 2.1
Name: word-to-pdf-converter
Version: 0.1.1
Summary: This is a simple word to pdf converter.
Author: Harshit Mishra
Author-email: harshit707125@gmail.com
Requires-Python: >=3.10,<4.0
Classifier: Programming Language :: Python :: 3
Classifier: Programming Language :: Python :: 3.10
Classifier: Programming Language :: Python :: 3.11
Classifier: Programming Language :: Python :: 3.12
Requires-Dist: flask (>=3.0.3,<4.0.0)
Requires-Dist: pdfkit (>=1.0.0,<2.0.0)
Requires-Dist: python-docx (>=1.1.2,<2.0.0)
Requires-Dist: pywin32 (>=306,<307)
Requires-Dist: reportlab (>=4.2.0,<5.0.0)
Requires-Dist: requests (>=2.32.3,<3.0.0)
